Tool.py
viytestlib/__init__.py
viytestlib/viylibone.py
viytestlib-1.0.0.dist-info/METADATA
viytestlib-1.0.0.dist-info/RECORD
viytestlib-1.0.0.dist-info/WHEEL
viytestlib-1.0.0.dist-info/top_level.txt
