Metadata-Version: 2.1
Name: viytestlib
Version: 1.0.0
Summary: this is a lib
Home-page: https://github.com/Viy/Python_code
Author: Viy
Author-email: feng743588510@163.com
License: MIT
Platform: UNKNOWN
